torch_attentions/__init__.py
torch_attentions/channel.py
torch_attentions/spatial.py
torch_attentions-0.1.4.dist-info/METADATA
torch_attentions-0.1.4.dist-info/WHEEL
torch_attentions-0.1.4.dist-info/RECORD
