Metadata-Version: 2.1
Name: torch-attentions
Version: 0.1.4
Summary: 
Author: javi22020
Author-email: 90896750+javi22020@users.noreply.github.com
Requires-Python: >=3.10,<4.0
Classifier: Programming Language :: Python :: 3
Classifier: Programming Language :: Python :: 3.10
Classifier: Programming Language :: Python :: 3.11
Classifier: Programming Language :: Python :: 3.12
